odoo/addons/edi_webservice_oca/README.rst
odoo/addons/edi_webservice_oca/__init__.py
odoo/addons/edi_webservice_oca/__manifest__.py
odoo/addons/edi_webservice_oca/components/__init__.py
odoo/addons/edi_webservice_oca/components/send.py
odoo/addons/edi_webservice_oca/demo/edi_backend.xml
odoo/addons/edi_webservice_oca/i18n/edi_webservice.pot
odoo/addons/edi_webservice_oca/i18n/edi_webservice_oca.pot
odoo/addons/edi_webservice_oca/i18n/es.po
odoo/addons/edi_webservice_oca/models/__init__.py
odoo/addons/edi_webservice_oca/models/edi_backend.py
odoo/addons/edi_webservice_oca/readme/CONFIGURATION.rst
odoo/addons/edi_webservice_oca/readme/CONTRIBUTORS.rst
odoo/addons/edi_webservice_oca/readme/DESCRIPTION.rst
odoo/addons/edi_webservice_oca/security/ir.model.access.csv
odoo/addons/edi_webservice_oca/static/description/icon.png
odoo/addons/edi_webservice_oca/static/description/index.html
odoo/addons/edi_webservice_oca/tests/__init__.py
odoo/addons/edi_webservice_oca/tests/common.py
odoo/addons/edi_webservice_oca/tests/test_backend.py
odoo/addons/edi_webservice_oca/tests/test_send.py
odoo/addons/edi_webservice_oca/views/edi_backend.xml
odoo14_addon_edi_webservice_oca-14.0.1.4.1.dist-info/METADATA
odoo14_addon_edi_webservice_oca-14.0.1.4.1.dist-info/WHEEL
odoo14_addon_edi_webservice_oca-14.0.1.4.1.dist-info/top_level.txt
odoo14_addon_edi_webservice_oca-14.0.1.4.1.dist-info/RECORD
